__devtools_builtin.pth
__devtools_builtin.py
py_devtools_builtin-1.1.0.dist-info/LICENSE.txt
py_devtools_builtin-1.1.0.dist-info/WHEEL
py_devtools_builtin-1.1.0.dist-info/METADATA
py_devtools_builtin-1.1.0.dist-info/RECORD
