Metadata-Version: 2.1
Name: py-devtools-builtin
Version: 1.1.0
Summary: Add devtools.debug() to python builtins
Home-page: https://github.com/Cielquan/py-devtools-builtin
License: Unlicense
Keywords: python-devtools,python,builtin,debugging
Author: Cielquan
Author-email: cielquan@protonmail.com
Requires-Python: >=3.6,<4.0
Classifier: Development Status :: 5 - Production/Stable
Classifier: Intended Audience :: Developers
Classifier: License :: OSI Approved :: The Unlicense (Unlicense)
Classifier: License :: Other/Proprietary License
Classifier: Operating System :: OS Independent
Classifier: Programming Language :: Python
Classifier: Programming Language :: Python :: 3
Classifier: Programming Language :: Python :: 3 :: Only
Classifier: Programming Language :: Python :: 3.10
Classifier: Programming Language :: Python :: 3.6
Classifier: Programming Language :: Python :: 3.7
Classifier: Programming Language :: Python :: 3.8
Classifier: Programming Language :: Python :: 3.9
Classifier: Programming Language :: Python :: Implementation :: CPython
Classifier: Topic :: Software Development
Requires-Dist: devtools[pygments]
Project-URL: Repository, https://github.com/Cielquan/py-devtools-builtin
